easytxt/__init__.py
easytxt/abbreviations.py
easytxt/config.py
easytxt/html.py
easytxt/sentences.py
easytxt/text.py
easytxt/parsers/__init__.py
easytxt/parsers/table.py
easytxt/parsers/text.py
tests/factory/__init__.py
tests/factory/features_samples.py
tests/factory/raw_sentences_samples.py
tests/factory/sentences_samples.py
tests/factory/string_samples.py
tests/factory/table_samples.py
tests/factory/text_samples.py
tests/parsers/__init__.py
tests/parsers/test_init.py
tests/parsers/test_table.py
tests/parsers/test_text.py
easytxt-0.1.2.dist-info/LICENSE
easytxt-0.1.2.dist-info/METADATA
easytxt-0.1.2.dist-info/WHEEL
easytxt-0.1.2.dist-info/top_level.txt
easytxt-0.1.2.dist-info/RECORD
