Metadata-Version: 2.1
Name: easytxt
Version: 0.1.2
Summary: Text manipulation and normalization library
Home-page: https://github.com/sitegroove/easytxt
Author: Rok Grabnar
Author-email: grabnarrok@gmail.com
License: BSD 3-Clause
Project-URL: Bug Reports, https://github.com/sitegroove/easytxt/issues
Project-URL: Source, https://github.com/sitegroove/easytxt
Project-URL: Documentation, https://github.com/sitegroove/easytxt
Classifier: Development Status :: 2 - Pre-Alpha
Classifier: Intended Audience :: Developers
Classifier: License :: OSI Approved :: BSD License
Classifier: Natural Language :: English
Classifier: Operating System :: OS Independent
Classifier: Programming Language :: Python :: 3
Requires-Python: >=3.8
License-File: LICENSE
Requires-Dist: ftfy
Requires-Dist: pyquery
Requires-Dist: number-parser
